rumbledb/__init__.py
rumbledb/rumbledb.py
rumbledb-1.22.0.dist-info/licenses/LICENSE
rumbledblivy/__init__.py
rumbledblivy/rumbledb.py
rumbledb-1.22.0.dist-info/METADATA
rumbledb-1.22.0.dist-info/WHEEL
rumbledb-1.22.0.dist-info/top_level.txt
rumbledb-1.22.0.dist-info/RECORD
